COPYING.txt
MANIFEST.in
setup.cfg
setup.py
SQLBase7_SA.egg-info/PKG-INFO
SQLBase7_SA.egg-info/SOURCES.txt
SQLBase7_SA.egg-info/dependency_links.txt
SQLBase7_SA.egg-info/entry_points.txt
SQLBase7_SA.egg-info/requires.txt
SQLBase7_SA.egg-info/top_level.txt
sqlbase7_sa/__init__.py
sqlbase7_sa/_version.py
sqlbase7_sa/sqlbase7.py
sqlbase7_sa/sqlbase7_sa05.py
sqlbase7_sa/sqlbase7_sa06.py
sqlbase7_sa/tests/__init__.py