Metadata-Version: 1.0
Name: SQLBase7-SA
Version: 0.1b4
Summary: SQLAlchemy dialect for Centura SQLBase v7
Home-page: http://sqlbase7-sa.edbob.org/
Author: Lance Edgar
Author-email: lance@edbob.org
License: GNU GPL v3
Platform: UNKNOWN
Classifier: Development Status :: 4 - Beta
Classifier: Environment :: Plugins
Classifier: Environment :: Win32 (MS Windows)
Classifier: Intended Audience :: Developers
Classifier: License :: OSI Approved :: GNU General Public License (GPL)
Classifier: Natural Language :: English
Classifier: Operating System :: Microsoft :: Windows
Classifier: Programming Language :: Python
Classifier: Programming Language :: Python :: 2.5
Classifier: Programming Language :: Python :: 2.6
Classifier: Topic :: Database
Classifier: Topic :: Software Development :: Libraries :: Python Modules
